gerenciador_projetos/__init__.py
gerenciador_projetos/interface.py
gerenciador_projetos-1.0.0.dist-info/LICENSE
gerenciador_projetos-1.0.0.dist-info/METADATA
gerenciador_projetos-1.0.0.dist-info/WHEEL
gerenciador_projetos-1.0.0.dist-info/entry_points.txt
gerenciador_projetos-1.0.0.dist-info/top_level.txt
gerenciador_projetos-1.0.0.dist-info/RECORD
